buckets/__init__.py
buckets/exceptions.py
buckets/fields.py
buckets/serializers.py
buckets/storage.py
buckets/urls.py
buckets/utils.py
buckets/views.py
buckets/widgets.py
buckets/__pycache__/__init__.cpython-35.pyc
buckets/__pycache__/defaults.cpython-35.pyc
buckets/__pycache__/exceptions.cpython-35.pyc
buckets/__pycache__/fields.cpython-35.pyc
buckets/__pycache__/forms.cpython-35.pyc
buckets/__pycache__/serializers.cpython-35.pyc
buckets/__pycache__/storage.cpython-35.pyc
buckets/__pycache__/urls.cpython-35.pyc
buckets/__pycache__/utils.cpython-35.pyc
buckets/__pycache__/views.cpython-35.pyc
buckets/__pycache__/widgets.cpython-35.pyc
buckets/static/buckets/css/buckets.css
buckets/static/buckets/js/script.js
buckets/test/__init__.py
buckets/test/errors.py
buckets/test/mocks.py
buckets/test/storage.py
buckets/test/urls.py
buckets/test/views.py
buckets/test/__pycache__/__init__.cpython-35.pyc
buckets/test/__pycache__/errors.cpython-35.pyc
buckets/test/__pycache__/mocks.cpython-35.pyc
buckets/test/__pycache__/storage.cpython-35.pyc
buckets/test/__pycache__/urls.cpython-35.pyc
buckets/test/__pycache__/utils.cpython-35.pyc
buckets/test/__pycache__/views.cpython-35.pyc
django_buckets-0.1.25.dist-info/DESCRIPTION.rst
django_buckets-0.1.25.dist-info/METADATA
django_buckets-0.1.25.dist-info/RECORD
django_buckets-0.1.25.dist-info/WHEEL
django_buckets-0.1.25.dist-info/metadata.json
django_buckets-0.1.25.dist-info/top_level.txt
