Metadata-Version: 2.0
Name: django-buckets
Version: 0.1.25
Summary: Upload files to S3 using pre-signed URLs.
Home-page: https://github.com/Cadasta/django-buckets
Author: Oliver Roick
Author-email: oroick@cadasta.org
License: AGPL
Platform: UNKNOWN
Classifier: Development Status :: 3 - Alpha
Classifier: Environment :: Web Environment
Classifier: Framework :: Django :: 1.9
Classifier: Intended Audience :: Developers
Classifier: License :: OSI Approved :: GNU Affero General Public License v3
Classifier: Operating System :: OS Independent
Classifier: Natural Language :: English
Classifier: Programming Language :: Python :: 3.5
Classifier: Topic :: Internet :: WWW/HTTP
Requires-Dist: boto3 (==1.7.4)
